README.rst
monetary2words.py
setup.py
monetary2words.egg-info/PKG-INFO
monetary2words.egg-info/SOURCES.txt
monetary2words.egg-info/dependency_links.txt
monetary2words.egg-info/requires.txt
monetary2words.egg-info/top_level.txt