Metadata-Version: 1.0
Name: monetary2words
Version: 0.3.0
Summary: UNKNOWN
Home-page: https://github.com/focusate/extra-tools
Author: Focusate
Author-email: dev@focusate.eu
License: MIT
Platform: UNKNOWN
